AUTHORS.rst
CONTRIBUTING.rst
HISTORY.rst
LICENSE
MANIFEST.in
README.rst
setup.cfg
setup.py
docs/Makefile
docs/authors.rst
docs/conf.py
docs/contributing.rst
docs/history.rst
docs/index.rst
docs/installation.rst
docs/make.bat
docs/readme.rst
docs/usage.rst
ocrtool/__init__.py
ocrtool/ocrtool.py
ocrtool.egg-info/PKG-INFO
ocrtool.egg-info/SOURCES.txt
ocrtool.egg-info/dependency_links.txt
ocrtool.egg-info/entry_points.txt
ocrtool.egg-info/not-zip-safe
ocrtool.egg-info/requires.txt
ocrtool.egg-info/top_level.txt
tests/__init__.py
tests/test_ocrtool.py