Metadata-Version: 1.1
Name: ocrtool
Version: 0.1.1
Summary: change image to txt with baidu-ocr
Home-page: https://github.com/wwj718/ocrtool
Author: wenjie wu
Author-email: wuwenjie@gmail.com
License: BSD license
Keywords: ocrtool
Platform: UNKNOWN
Classifier: Development Status :: 2 - Pre-Alpha
Classifier: Intended Audience :: Developers
Classifier: License :: OSI Approved :: BSD License
Classifier: Natural Language :: English
Classifier: Programming Language :: Python :: 2
Classifier: Programming Language :: Python :: 2.6
Classifier: Programming Language :: Python :: 2.7
Classifier: Programming Language :: Python :: 3
Classifier: Programming Language :: Python :: 3.3
Classifier: Programming Language :: Python :: 3.4
Classifier: Programming Language :: Python :: 3.5
